lostlifevalue.py
lostlifevalue-0.0.8.dist-info/METADATA
lostlifevalue-0.0.8.dist-info/WHEEL
lostlifevalue-0.0.8.dist-info/entry_points.txt
lostlifevalue-0.0.8.dist-info/top_level.txt
lostlifevalue-0.0.8.dist-info/RECORD
