Metadata-Version: 2.1
Name: lostlifevalue
Version: 0.0.8
Summary: A package to find out the true extent of the damage caused by Covid-19 to the country.
Home-page: https://github.com/Kiuchi424/Lostlifevalue
Author: Kiuchi_424
Author-email: s1922059@stu.musashino-u.ac.jp
License: UNKNOWN
Project-URL: Lostlifevalue, https://github.com/Kiuchi424/Lostlifevalue
Platform: UNKNOWN
Classifier: Programming Language :: Python :: 3
Classifier: License :: OSI Approved :: MIT License
Classifier: Operating System :: OS Independent
Requires-Python: >=3.6
